Metadata-Version: 2.1
Name: micropython-wifi-communication
Version: 0.0.9
Summary: um substituto para em vez de uma comunicação RF utilizar wifi
Home-page: UNKNOWN
Author: issei momonge
Author-email: mggyggf@gmail.com
License: MIT License
Keywords: socket communication via wifi
Platform: UNKNOWN
License-File: LICENCE
